LICENSE
README.md
setup.cfg
setup.py
config/__init__.py
config/__main__.py
config/conf.py
config/data.py
config_oc.egg-info/PKG-INFO
config_oc.egg-info/SOURCES.txt
config_oc.egg-info/dependency_links.txt
config_oc.egg-info/requires.txt
config_oc.egg-info/top_level.txt
config_oc.egg-info/zip-safe