Metadata-Version: 2.1
Name: config-oc
Version: 1.0.2
Summary: Handles loading loading configuration files based on hostname
Home-page: https://ouroboroscoding.com/config/
Author: Chris Nasr - Ouroboros Coding Inc.
Author-email: chris@ouroboroscoding.com
License: MIT
Project-URL: Documentation, https://ouroboroscoding.com/config/
Project-URL: Source, https://github.com/ouroboroscoding/config-python
Project-URL: Tracker, https://github.com/ouroboroscoding/config-python/issues
Keywords: config,configuration,host specific configuration
Requires-Python: >=3.10
License-File: LICENSE
